[
  {
    "text": "Section 1182(e) of the Social Security Act",
    "startPosition": 809,
    "endPosition": 851,
    "normCite": "42 usc 1320e-1",
    "citeType": "USC",
    "altCite": "42 usc 1320e-1",
    "pinCiteStr": "",
    "pageRangeStr": "",
    "nodeId": 0,
    "section": "",
    "sectionAndSubSection": "",
    "isShortCite": false
  },
  {
    "text": "42 U.S.C. 1320e–1(e)",
    "startPosition": 853,
    "endPosition": 873,
    "normCite": "42 usc 1320e-1",
    "citeType": "USC",
    "altCite": "",
    "pinCiteStr": "",
    "pageRangeStr": "",
    "nodeId": 0,
    "section": "42 U.S.C. 1320e-1",
    "sectionAndSubSection": "42 U.S.C. 1320e-1(e)",
    "isShortCite": false
  },
  {
    "text": "section 1115A)",
    "startPosition": 1333,
    "endPosition": 1347,
    "normCite": "",
    "citeType": "",
    "altCite": "",
    "pinCiteStr": "",
    "pageRangeStr": "",
    "nodeId": 0,
    "section": "",
    "sectionAndSubSection": "",
    "isShortCite": false
  },
  {
    "text": "title XVIII",
    "startPosition": 1389,
    "endPosition": 1400,
    "normCite": "",
    "citeType": "",
    "altCite": "",
    "pinCiteStr": "",
    "pageRangeStr": "",
    "nodeId": 0,
    "section": "",
    "sectionAndSubSection": "",
    "isShortCite": false
  },
  {
    "text": "section 1128B",
    "startPosition": 1484,
    "endPosition": 1497,
    "normCite": "",
    "citeType": "",
    "altCite": "",
    "pinCiteStr": "",
    "pageRangeStr": "",
    "nodeId": 0,
    "section": "",
    "sectionAndSubSection": "",
    "isShortCite": true
  },
  {
    "text": "chapter 89 of title 5",
    "startPosition": 1572,
    "endPosition": 1593,
    "normCite": "",
    "citeType": "",
    "altCite": "",
    "pinCiteStr": "",
    "pageRangeStr": "",
    "nodeId": 0,
    "section": "",
    "sectionAndSubSection": "",
    "isShortCite": false
  },
  {
    "text": "section 1852(o), section 1860D–12(h), section 1902(a)(88), section 1932(b)(9)",
    "startPosition": 1853,
    "endPosition": 1930,
    "normCite": "",
    "citeType": "",
    "altCite": "",
    "pinCiteStr": "",
    "pageRangeStr": "",
    "nodeId": 0,
    "section": "",
    "sectionAndSubSection": "",
    "isShortCite": false
  },
  {
    "text": "section 2102(e)",
    "startPosition": 1935,
    "endPosition": 1950,
    "normCite": "42 usc 1397bb",
    "citeType": "USC",
    "altCite": "42 usc 1397bb",
    "pinCiteStr": "",
    "pageRangeStr": "",
    "nodeId": 0,
    "section": "",
    "sectionAndSubSection": "",
    "isShortCite": true
  },
  {
    "text": "section 1115, section 1115A",
    "startPosition": 1958,
    "endPosition": 1985,
    "normCite": "",
    "citeType": "",
    "altCite": "",
    "pinCiteStr": "",
    "pageRangeStr": "",
    "nodeId": 0,
    "section": "",
    "sectionAndSubSection": "",
    "isShortCite": false
  },
  {
    "text": "Section 1902(a) of the Social Security Act",
    "startPosition": 2090,
    "endPosition": 2132,
    "normCite": "42 usc 1396a",
    "citeType": "USC",
    "altCite": "42 usc 1396a",
    "pinCiteStr": "",
    "pageRangeStr": "",
    "nodeId": 0,
    "section": "",
    "sectionAndSubSection": "",
    "isShortCite": false
  },
  {
    "text": "42 U.S.C. 1396a(a)",
    "startPosition": 2134,
    "endPosition": 2152,
    "normCite": "42 usc 1396a",
    "citeType": "USC",
    "altCite": "",
    "pinCiteStr": "",
    "pageRangeStr": "",
    "nodeId": 0,
    "section": "42 U.S.C. 1396a",
    "sectionAndSubSection": "42 U.S.C. 1396a(a)",
    "isShortCite": false
  },
  {
    "text": "paragraph (87)(D)",
    "startPosition": 2225,
    "endPosition": 2242,
    "normCite": "",
    "citeType": "",
    "altCite": "",
    "pinCiteStr": "",
    "pageRangeStr": "",
    "nodeId": 0,
    "section": "",
    "sectionAndSubSection": "",
    "isShortCite": false
  },
  {
    "text": "section 1182(e)",
    "startPosition": 2414,
    "endPosition": 2429,
    "normCite": "42 usc 1320e-1",
    "citeType": "USC",
    "altCite": "42 usc 1320e-1",
    "pinCiteStr": "",
    "pageRangeStr": "",
    "nodeId": 0,
    "section": "",
    "sectionAndSubSection": "",
    "isShortCite": true
  },
  {
    "text": "Section 1932(b) of the Social Security Act",
    "startPosition": 2584,
    "endPosition": 2626,
    "normCite": "42 usc 1396u-2",
    "citeType": "USC",
    "altCite": "42 usc 1396u-2",
    "pinCiteStr": "",
    "pageRangeStr": "",
    "nodeId": 0,
    "section": "",
    "sectionAndSubSection": "",
    "isShortCite": false
  },
  {
    "text": "42 U.S.C. 1396u–2(b)",
    "startPosition": 2628,
    "endPosition": 2648,
    "normCite": "42 usc 1396u-2",
    "citeType": "USC",
    "altCite": "",
    "pinCiteStr": "",
    "pageRangeStr": "",
    "nodeId": 0,
    "section": "42 U.S.C. 1396u-2",
    "sectionAndSubSection": "42 U.S.C. 1396u-2(b)",
    "isShortCite": false
  },
  {
    "text": "section 1182(e)",
    "startPosition": 2783,
    "endPosition": 2798,
    "normCite": "42 usc 1320e-1",
    "citeType": "USC",
    "altCite": "42 usc 1320e-1",
    "pinCiteStr": "",
    "pageRangeStr": "",
    "nodeId": 0,
    "section": "",
    "sectionAndSubSection": "",
    "isShortCite": true
  },
  {
    "text": "section 438.2 of title 42, Code of Federal Regulations",
    "startPosition": 3066,
    "endPosition": 3120,
    "normCite": "",
    "citeType": "",
    "altCite": "",
    "pinCiteStr": "",
    "pageRangeStr": "",
    "nodeId": 0,
    "section": "",
    "sectionAndSubSection": "",
    "isShortCite": false
  },
  {
    "text": "Section 2102 of the Social Security Act",
    "startPosition": 3314,
    "endPosition": 3353,
    "normCite": "42 usc 1397bb",
    "citeType": "USC",
    "altCite": "42 usc 1397bb",
    "pinCiteStr": "",
    "pageRangeStr": "",
    "nodeId": 0,
    "section": "",
    "sectionAndSubSection": "",
    "isShortCite": false
  },
  {
    "text": "42 U.S.C. 1397bb",
    "startPosition": 3355,
    "endPosition": 3371,
    "normCite": "42 usc 1397bb",
    "citeType": "USC",
    "altCite": "",
    "pinCiteStr": "",
    "pageRangeStr": "",
    "nodeId": 0,
    "section": "42 U.S.C. 1397bb",
    "sectionAndSubSection": "42 U.S.C. 1397bb",
    "isShortCite": false
  },
  {
    "text": "section 1182(e)",
    "startPosition": 3594,
    "endPosition": 3609,
    "normCite": "42 usc 1320e-1",
    "citeType": "USC",
    "altCite": "42 usc 1320e-1",
    "pinCiteStr": "",
    "pageRangeStr": "",
    "nodeId": 0,
    "section": "",
    "sectionAndSubSection": "",
    "isShortCite": true
  },
  {
    "text": "Medicare Advantage Section 1852 of the Social Security Act",
    "startPosition": 3737,
    "endPosition": 3795,
    "normCite": "",
    "citeType": "",
    "altCite": "",
    "pinCiteStr": "",
    "pageRangeStr": "",
    "nodeId": 0,
    "section": "",
    "sectionAndSubSection": "",
    "isShortCite": false
  },
  {
    "text": "42 U.S.C. 1395w–22",
    "startPosition": 3797,
    "endPosition": 3815,
    "normCite": "42 usc 1395w-22",
    "citeType": "USC",
    "altCite": "",
    "pinCiteStr": "",
    "pageRangeStr": "",
    "nodeId": 0,
    "section": "42 U.S.C. 1395w-22",
    "sectionAndSubSection": "42 U.S.C. 1395w-22",
    "isShortCite": false
  },
  {
    "text": "section 1182(e)",
    "startPosition": 3951,
    "endPosition": 3966,
    "normCite": "42 usc 1320e-1",
    "citeType": "USC",
    "altCite": "42 usc 1320e-1",
    "pinCiteStr": "",
    "pageRangeStr": "",
    "nodeId": 0,
    "section": "",
    "sectionAndSubSection": "",
    "isShortCite": true
  },
  {
    "text": "D Section 1860D–12 of the Social Security Act",
    "startPosition": 4250,
    "endPosition": 4295,
    "normCite": "",
    "citeType": "",
    "altCite": "",
    "pinCiteStr": "",
    "pageRangeStr": "",
    "nodeId": 0,
    "section": "",
    "sectionAndSubSection": "",
    "isShortCite": false
  },
  {
    "text": "42 U.S.C. 1395w–112",
    "startPosition": 4297,
    "endPosition": 4316,
    "normCite": "42 usc 1395w-112",
    "citeType": "USC",
    "altCite": "",
    "pinCiteStr": "",
    "pageRangeStr": "",
    "nodeId": 0,
    "section": "42 U.S.C. 1395w-112",
    "sectionAndSubSection": "42 U.S.C. 1395w-112",
    "isShortCite": false
  },
  {
    "text": "section 1182(e)",
    "startPosition": 4452,
    "endPosition": 4467,
    "normCite": "42 usc 1320e-1",
    "citeType": "USC",
    "altCite": "42 usc 1320e-1",
    "pinCiteStr": "",
    "pageRangeStr": "",
    "nodeId": 0,
    "section": "",
    "sectionAndSubSection": "",
    "isShortCite": true
  },
  {
    "text": "PUBLIC HEALTH FUND Section 4002(b) of the Patient Protection and Affordable Care Act",
    "startPosition": 4862,
    "endPosition": 4946,
    "normCite": "",
    "citeType": "",
    "altCite": "",
    "pinCiteStr": "",
    "pageRangeStr": "",
    "nodeId": 0,
    "section": "",
    "sectionAndSubSection": "",
    "isShortCite": false
  },
  {
    "text": "42 U.S.C. 300u–11",
    "startPosition": 4948,
    "endPosition": 4965,
    "normCite": "42 usc 300u-11",
    "citeType": "USC",
    "altCite": "",
    "pinCiteStr": "",
    "pageRangeStr": "",
    "nodeId": 0,
    "section": "42 U.S.C. 300u-11",
    "sectionAndSubSection": "42 U.S.C. 300u-11",
    "isShortCite": false
  },
  {
    "text": "paragraphs (7), (8), and (9)",
    "startPosition": 4990,
    "endPosition": 5018,
    "normCite": "",
    "citeType": "",
    "altCite": "",
    "pinCiteStr": "",
    "pageRangeStr": "",
    "nodeId": 0,
    "section": "",
    "sectionAndSubSection": "",
    "isShortCite": false
  }
]
