[{"text":"2021 states","startPosition":2056,"endPosition":2067,"normCite":"2021 stat es","citeType":"StatutesAtLarge","altCite":"","pinCiteStr":"","pageRangeStr":"","nodeId":0,"section":"","sectionAndSubSection":"","isShortCite":false},{"text":"subsection (a)(2)","startPosition":6314,"endPosition":6331,"normCite":"","citeType":"","altCite":"","pinCiteStr":"","pageRangeStr":"","nodeId":0,"section":"","sectionAndSubSection":"","isShortCite":false},{"text":"subsection (f)(2)(A)","startPosition":6440,"endPosition":6460,"normCite":"","citeType":"","altCite":"","pinCiteStr":"","pageRangeStr":"","nodeId":0,"section":"","sectionAndSubSection":"","isShortCite":false},{"text":"subsections (a) and (b)","startPosition":6485,"endPosition":6508,"normCite":"","citeType":"","altCite":"","pinCiteStr":"","pageRangeStr":"","nodeId":0,"section":"","sectionAndSubSection":"","isShortCite":false},{"text":"subsection (f)(3)","startPosition":6586,"endPosition":6603,"normCite":"","citeType":"","altCite":"","pinCiteStr":"","pageRangeStr":"","nodeId":0,"section":"","sectionAndSubSection":"","isShortCite":false},{"text":"subsection (f)(3)","startPosition":6651,"endPosition":6668,"normCite":"","citeType":"","altCite":"","pinCiteStr":"","pageRangeStr":"","nodeId":0,"section":"","sectionAndSubSection":"","isShortCite":false},{"text":"subsection (f)(2)(B)","startPosition":6779,"endPosition":6799,"normCite":"","citeType":"","altCite":"","pinCiteStr":"","pageRangeStr":"","nodeId":0,"section":"","sectionAndSubSection":"","isShortCite":false},{"text":"subsections (a) and (b)","startPosition":6824,"endPosition":6847,"normCite":"","citeType":"","altCite":"","pinCiteStr":"","pageRangeStr":"","nodeId":0,"section":"","sectionAndSubSection":"","isShortCite":false},{"text":"subsection (f)(3)","startPosition":6926,"endPosition":6943,"normCite":"","citeType":"","altCite":"","pinCiteStr":"","pageRangeStr":"","nodeId":0,"section":"","sectionAndSubSection":"","isShortCite":false},{"text":"subsection (a) and (b)","startPosition":7081,"endPosition":7103,"normCite":"","citeType":"","altCite":"","pinCiteStr":"","pageRangeStr":"","nodeId":0,"section":"","sectionAndSubSection":"","isShortCite":false},{"text":"clause (ii)","startPosition":7507,"endPosition":7518,"normCite":"","citeType":"","altCite":"","pinCiteStr":"","pageRangeStr":"","nodeId":0,"section":"","sectionAndSubSection":"","isShortCite":false},{"text":"subparagraph (A)","startPosition":7543,"endPosition":7559,"normCite":"","citeType":"","altCite":"","pinCiteStr":"","pageRangeStr":"","nodeId":0,"section":"","sectionAndSubSection":"","isShortCite":false},{"text":"subparagraph (A)","startPosition":7805,"endPosition":7821,"normCite":"","citeType":"","altCite":"","pinCiteStr":"","pageRangeStr":"","nodeId":0,"section":"","sectionAndSubSection":"","isShortCite":false},{"text":"subsections (a) and (b)","startPosition":8198,"endPosition":8221,"normCite":"","citeType":"","altCite":"","pinCiteStr":"","pageRangeStr":"","nodeId":0,"section":"","sectionAndSubSection":"","isShortCite":false},{"text":"subsection (e)(2)(A)","startPosition":8547,"endPosition":8567,"normCite":"","citeType":"","altCite":"","pinCiteStr":"","pageRangeStr":"","nodeId":0,"section":"","sectionAndSubSection":"","isShortCite":false},{"text":"subsections (a) and (b)","startPosition":8981,"endPosition":9004,"normCite":"","citeType":"","altCite":"","pinCiteStr":"","pageRangeStr":"","nodeId":0,"section":"","sectionAndSubSection":"","isShortCite":false},{"text":"title V of the National Security Act of 1947","startPosition":9086,"endPosition":9130,"normCite":"","citeType":"","altCite":"","pinCiteStr":"","pageRangeStr":"","nodeId":0,"section":"","sectionAndSubSection":"","isShortCite":false},{"text":"50 U.S.C. 3091","startPosition":9132,"endPosition":9146,"normCite":"50 usc 3091","citeType":"USC","altCite":"50 U.S.C. ยง 3091","pinCiteStr":"","pageRangeStr":"","nodeId":0,"section":"50 U.S.C. 3091","sectionAndSubSection":"50 U.S.C. 3091","isShortCite":false},{"text":"section 101(a) of title 10","startPosition":9386,"endPosition":9412,"normCite":"","citeType":"","altCite":"","pinCiteStr":"","pageRangeStr":"","nodeId":0,"section":"","sectionAndSubSection":"","isShortCite":false},{"text":"subparagraph (A)","startPosition":9728,"endPosition":9744,"normCite":"","citeType":"","altCite":"","pinCiteStr":"","pageRangeStr":"","nodeId":0,"section":"","sectionAndSubSection":"","isShortCite":false},{"text":"subsection (f)(3)","startPosition":12520,"endPosition":12537,"normCite":"","citeType":"","altCite":"","pinCiteStr":"","pageRangeStr":"","nodeId":0,"section":"","sectionAndSubSection":"","isShortCite":false},{"text":"subparagraph (A)","startPosition":14252,"endPosition":14268,"normCite":"","citeType":"","altCite":"","pinCiteStr":"","pageRangeStr":"","nodeId":0,"section":"","sectionAndSubSection":"","isShortCite":false},{"text":"section 800.208 of title 31","startPosition":14742,"endPosition":14769,"normCite":"","citeType":"","altCite":"","pinCiteStr":"","pageRangeStr":"","nodeId":0,"section":"","sectionAndSubSection":"","isShortCite":false},{"text":"section 105 of title 5","startPosition":14928,"endPosition":14950,"normCite":"","citeType":"","altCite":"","pinCiteStr":"","pageRangeStr":"","nodeId":0,"section":"","sectionAndSubSection":"","isShortCite":false},{"text":"section 4872(d) of title 10","startPosition":15070,"endPosition":15097,"normCite":"","citeType":"","altCite":"","pinCiteStr":"","pageRangeStr":"","nodeId":0,"section":"","sectionAndSubSection":"","isShortCite":false}]